<annotation>
    <folder>VOC2007</folder>
    <filename>002457.jpg</filename>
    <source>
        <database>My Database</database>
        <annotation>VOC2007</annotation>
        <image>flickr</image>
        <flickrid>NULL</flickrid>
    </source>
    <owner>
        <flickrid>NULL</flickrid>
        <name>QQ974573656</name>
    </owner>
    <size>
        <width>330</width>
        <height>280</height>
        <depth>3</depth>
    </size>
    <segmented>0</segmented>
    <object>
        <name>1</name>
        <pose>Unspecified</pose>
        <truncated>0</truncated>
        <difficult>0</difficult>
        <bndbox>
            <xmin>177</xmin>
            <ymin>13</ymin>
            <xmax>209</xmax>
            <ymax>19</ymax>
        </bndbox>
    </object>
    <object>
        <name>1</name>
        <pose>Unspecified</pose>
        <truncated>0</truncated>
        <difficult>0</difficult>
        <bndbox>
            <xmin>265</xmin>
            <ymin>5</ymin>
            <xmax>280</xmax>
            <ymax>13</ymax>
        </bndbox>
    </object>
    <object>
        <name>1</name>
        <pose>Unspecified</pose>
        <truncated>0</truncated>
        <difficult>0</difficult>
        <bndbox>
            <xmin>261</xmin>
            <ymin>29</ymin>
            <xmax>284</xmax>
            <ymax>36</ymax>
        </bndbox>
    </object>
    <object>
        <name>1</name>
        <pose>Unspecified</pose>
        <truncated>0</truncated>
        <difficult>0</difficult>
        <bndbox>
            <xmin>163</xmin>
            <ymin>99</ymin>
            <xmax>179</xmax>
            <ymax>107</ymax>
        </bndbox>
    </object>
    <object>
        <name>1</name>
        <pose>Unspecified</pose>
        <truncated>0</truncated>
        <difficult>0</difficult>
        <bndbox>
            <xmin>164</xmin>
            <ymin>123</ymin>
            <xmax>182</xmax>
            <ymax>130</ymax>
        </bndbox>
    </object>
    <object>
        <name>1</name>
        <pose>Unspecified</pose>
        <truncated>0</truncated>
        <difficult>0</difficult>
        <bndbox>
            <xmin>259</xmin>
            <ymin>154</ymin>
            <xmax>299</xmax>
            <ymax>160</ymax>
        </bndbox>
    </object>
    <object>
        <name>1</name>
        <pose>Unspecified</pose>
        <truncated>0</truncated>
        <difficult>0</difficult>
        <bndbox>
            <xmin>165</xmin>
            <ymin>194</ymin>
            <xmax>179</xmax>
            <ymax>201</ymax>
        </bndbox>
    </object>
    <object>
        <name>1</name>
        <pose>Unspecified</pose>
        <truncated>0</truncated>
        <difficult>0</difficult>
        <bndbox>
            <xmin>164</xmin>
            <ymin>218</ymin>
            <xmax>180</xmax>
            <ymax>225</ymax>
        </bndbox>
    </object>
    <object>
        <name>1</name>
        <pose>Unspecified</pose>
        <truncated>0</truncated>
        <difficult>0</difficult>
        <bndbox>
            <xmin>148</xmin>
            <ymin>237</ymin>
            <xmax>161</xmax>
            <ymax>243</ymax>
        </bndbox>
    </object>
    <object>
        <name>1</name>
        <pose>Unspecified</pose>
        <truncated>0</truncated>
        <difficult>0</difficult>
        <bndbox>
            <xmin>142</xmin>
            <ymin>261</ymin>
            <xmax>168</xmax>
            <ymax>267</ymax>
        </bndbox>
    </object>
</annotation>
